fastapi_toolkit/__init__.py
fastapi_toolkit/exceptions.py
fastapi_toolkit/py.typed
fastapi_toolkit/dependencies/__init__.py
fastapi_toolkit/dependencies/auth.py
fastapi_toolkit/dependencies/db.py
fastapi_toolkit/dependencies/user.py
fastapi_toolkit/models/__init__.py
fastapi_toolkit/models/auth.py
fastapi_toolkit/models/base.py
fastapi_toolkit/models/user.py
fastapi_toolkit/schemas/__init__.py
fastapi_toolkit/schemas/auth.py
fastapi_toolkit/schemas/db.py
fastapi_toolkit/schemas/user.py
fastapi_toolkit/services/__init__.py
fastapi_toolkit/services/auth.py
fastapi_toolkit/services/db.py
fastapi_toolkit/services/user.py
fastapi_toolkit/utils/__init__.py
fastapi_toolkit/utils/constants.py
fastapi_toolkit/utils/helper_functions.py
fastapi_toolkit/utils/security.py
aps_fastapi_toolkit-1.2.2.dist-info/METADATA
aps_fastapi_toolkit-1.2.2.dist-info/WHEEL
aps_fastapi_toolkit-1.2.2.dist-info/top_level.txt
aps_fastapi_toolkit-1.2.2.dist-info/RECORD
