Metadata-Version: 2.4
Name: aps_fastapi_toolkit
Version: 1.2.2
Summary: Common utils and services for FastAPI projects.
Author: Abhay Pratap Singh
Keywords: fastapi,jwt,authentication,database,sqlalchemy,security
Classifier: Intended Audience :: Developers
Classifier: Operating System :: OS Independent
Classifier: Programming Language :: Python :: 3
Classifier: Programming Language :: Python :: 3.12
Classifier: Framework :: FastAPI
Requires-Python: >=3.12
Requires-Dist: argon2-cffi==25.1.0
Requires-Dist: SQLAlchemy==2.0.43
Requires-Dist: PyJWT==2.10.1
Requires-Dist: fastapi==0.118.0
Requires-Dist: email-validator==2.3.0
Dynamic: author
Dynamic: classifier
Dynamic: description
Dynamic: description-content-type
Dynamic: keywords
Dynamic: requires-dist
Dynamic: requires-python
Dynamic: summary
